fmri_physio_log/__init__.py
fmri_physio_log/_generated.py
fmri_physio_log-0.3.3.dist-info/LICENSE
fmri_physio_log-0.3.3.dist-info/METADATA
fmri_physio_log-0.3.3.dist-info/WHEEL
fmri_physio_log-0.3.3.dist-info/RECORD
