Metadata-Version: 2.1
Name: fmri-physio-log
Version: 0.3.3
Summary: Parse Siemens PMU files
Home-page: https://github.com/andrewrosss/fmri-physio-log
License: MIT
Keywords: mri,siemens,pmu
Author: Andrew Ross
Author-email: andrew.ross.mail@gmail.com
Requires-Python: >=3.9,<4.0
Classifier: Development Status :: 4 - Beta
Classifier: License :: OSI Approved :: MIT License
Classifier: Programming Language :: Python :: 3
Classifier: Programming Language :: Python :: 3.9
Classifier: Programming Language :: Python :: 3.10
Classifier: Programming Language :: Python :: 3.11
Classifier: Programming Language :: Python :: 3.12
Classifier: Programming Language :: Python :: 3.0
Classifier: Topic :: Scientific/Engineering :: Medical Science Apps.
Project-URL: Documentation, https://github.com/andrewrosss/fmri-physio-log
Project-URL: Repository, https://github.com/andrewrosss/fmri-physio-log
